evo_cli/__init__.py
evo_cli/__main__.py
evo_cli/base.py
evo_cli/cli.py
evo_cli/miniconda_setup.py
evo_cli/ssh_setup.py
evo_cli-0.1.8.dist-info/licenses/LICENSE
evo_cli-0.1.8.dist-info/METADATA
evo_cli-0.1.8.dist-info/WHEEL
evo_cli-0.1.8.dist-info/entry_points.txt
evo_cli-0.1.8.dist-info/top_level.txt
evo_cli-0.1.8.dist-info/RECORD
