Metadata-Version: 2.4
Name: evo_cli
Version: 0.1.8
Summary: Awesome evo_cli created by maycuatroi
Home-page: https://github.com/maycuatroi/evo-cli/
Author: maycuatroi
License-File: LICENSE
Requires-Dist: paramiko>=2.7.0
Provides-Extra: test
Requires-Dist: pytest; extra == "test"
Requires-Dist: coverage; extra == "test"
Requires-Dist: flake8; extra == "test"
Requires-Dist: black; extra == "test"
Requires-Dist: isort; extra == "test"
Requires-Dist: pytest-cov; extra == "test"
Requires-Dist: mypy; extra == "test"
Requires-Dist: types-paramiko; extra == "test"
Requires-Dist: gitchangelog; extra == "test"
Requires-Dist: mkdocs; extra == "test"
Dynamic: author
Dynamic: description
Dynamic: description-content-type
Dynamic: home-page
Dynamic: license-file
Dynamic: provides-extra
Dynamic: requires-dist
Dynamic: summary
